terbinePyLibrary/__init__.py
terbine_py_library-1.0.0.dist-info/LICENSE.txt
terbine_py_library-1.0.0.dist-info/METADATA
terbine_py_library-1.0.0.dist-info/WHEEL
terbine_py_library-1.0.0.dist-info/top_level.txt
terbine_py_library-1.0.0.dist-info/RECORD
