Metadata-Version: 2.1
Name: terbine-py-library
Version: 1.0.0
Summary: Python modules used to connect to Terbine's API
Home-page: https://terbine.com/specifications/
Author: Jenal Sanchez
Author-email: jenal@terbine.com
License: UNKNOWN
Platform: UNKNOWN
Classifier: Programming Language :: Python :: 3
Classifier: License :: OSI Approved :: MIT License
Classifier: Operating System :: OS Independent
Requires-Python: >=3.6
